pt_fc_layers_viz
