Metadata-Version: 2.1
Name: pt-fc-layers-viz
Version: 0.3
Summary: A visualization tool for PyTorch fully connected layers.
Home-page: https://github.com/repetitioestmaterstudiorum/pt_fc_layers_viz
Author: repetitioestmaterstudiorum
Author-email: 44611591+repetitioestmaterstudiorum@users.noreply.github.com
